<?xml version="1.0" encoding="utf-8" ?>
<!--
Texture2D Icon { get; set; }
string Name { get; set; }
int LevelToAccess { get; set; }
int GoldToAccess { get; set; }
float ManaCost { get; set; }
float Range { get; set; }
float Cooldown { get; set; }
ESpell SpellType { get; set; }
float Duration { get; set; }
IBuffSpell.Skill { get; set; }
IBuffSpell.PercentageIncrease { get; set; }
IPassiveSpell.Skill { get; set; }
IPassiveSpell.PercentageIncrease { get; set; }
float PercentageDamage { get; set; }
-->
<Root>
  <Spell>
    <ID>1</ID>
    <Name>PowerHit</Name>
    <Description>This spell is buff</Description>
    <LevelToAccess>1</LevelToAccess>
    <GoldToAccess>0</GoldToAccess>
    <ManaCost>2</ManaCost>
    <Range>3</Range>
    <Cooldown>10</Cooldown>
    <SpellType>Buff</SpellType>
    <Duration>3</Duration>
    <Skill>Constitution</Skill>
    <Vital></Vital>
    <DamageStats></DamageStats>
    <PercentageIncreaseDecrease>150</PercentageIncreaseDecrease>
    <PercentageDamage>0</PercentageDamage>
  </Spell>
  <Spell>
    <ID>2</ID>
    <Name>MortalBlade</Name>
    <Description>This spell is passive</Description>
    <LevelToAccess>2</LevelToAccess>
    <GoldToAccess>0</GoldToAccess>
    <ManaCost>2</ManaCost>
    <Range>3</Range>
    <Cooldown>4</Cooldown>
    <SpellType>Passive</SpellType>
    <Duration>0</Duration>
    <Skill>Constitution</Skill>
    <Vital></Vital>
    <DamageStats></DamageStats>
    <PercentageIncreaseDecrease>150</PercentageIncreaseDecrease>
    <PercentageDamage>0</PercentageDamage>
  </Spell>
  <Spell>
    <ID>3</ID>
    <Name>BloodStorm</Name>
    <Description>This spell is damage</Description>
    <LevelToAccess>1</LevelToAccess>
    <GoldToAccess>0</GoldToAccess>
    <ManaCost>2</ManaCost>
    <Range>3</Range>
    <Cooldown>4</Cooldown>
    <SpellType>Damage</SpellType>
    <Duration>0</Duration>
    <Skill></Skill>
    <Vital></Vital>
    <DamageStats></DamageStats>
    <PercentageIncreaseDecrease>0</PercentageIncreaseDecrease>
    <PercentageDamage>200</PercentageDamage>
  </Spell>
  <Spell>
    <ID>4</ID>
    <Name>FuryShout</Name>
    <Description>This spell is weakness</Description>
    <LevelToAccess>1</LevelToAccess>
    <GoldToAccess>0</GoldToAccess>
    <ManaCost>2</ManaCost>
    <Range>3</Range>
    <Cooldown>17</Cooldown>
    <SpellType>Weakness</SpellType>
    <Duration>3</Duration>
    <Skill></Skill>
    <Vital>Health</Vital>
    <DamageStats></DamageStats>
    <PercentageIncreaseDecrease>25</PercentageIncreaseDecrease>
    <PercentageDamage>0</PercentageDamage>
  </Spell>
  <Spell>
    <ID>5</ID>
    <Name>StormStrike</Name>
    <Description>This spell is Dot</Description>
    <LevelToAccess>1</LevelToAccess>
    <GoldToAccess>0</GoldToAccess>
    <ManaCost>2</ManaCost>
    <Range>3</Range>
    <Cooldown>15</Cooldown>
    <SpellType>Dot</SpellType>
    <Duration>6</Duration>
    <Skill></Skill>
    <Vital></Vital>
    <DamageStats></DamageStats>
    <PercentageIncreaseDecrease>0</PercentageIncreaseDecrease>
    <PercentageDamage>20</PercentageDamage>
  </Spell>
</Root>